rej/__init__.py
rej/backend.py
rej-0.1.0.dist-info/LICENSE
rej-0.1.0.dist-info/METADATA
rej-0.1.0.dist-info/WHEEL
rej-0.1.0.dist-info/top_level.txt
rej-0.1.0.dist-info/RECORD
