Metadata-Version: 2.1
Name: rej
Version: 0.1.0
Summary: Interactive image registration tool for JupyterLab
Home-page: https://github.com/ceresimaging/rej
Author: Seth Nickell
Author-email: snickell@gmail.com
License: MIT
Platform: UNKNOWN
Classifier: License :: OSI Approved :: MIT License
Classifier: Programming Language :: Python :: 3
Classifier: Programming Language :: Python :: 3.7
Requires-Dist: ipywidgets
Requires-Dist: traitlets
